{
  "type": "GROUP",
"name": "All Requests",
"path": "",
"pathFormatted": "group_missing-name-b06d1",
"stats": {
    "name": "All Requests",
    "numberOfRequests": {
        "total": 81753,
        "ok": 25529,
        "ko": 56224
    },
    "minResponseTime": {
        "total": 0,
        "ok": 0,
        "ko": 0
    },
    "maxResponseTime": {
        "total": 19999,
        "ok": 19999,
        "ko": 198
    },
    "meanResponseTime": {
        "total": 490,
        "ok": 1565,
        "ko": 2
    },
    "standardDeviation": {
        "total": 2653,
        "ok": 4567,
        "ko": 7
    },
    "percentiles1": {
        "total": 1,
        "ok": 7,
        "ko": 1
    },
    "percentiles2": {
        "total": 4,
        "ok": 77,
        "ko": 2
    },
    "percentiles3": {
        "total": 98,
        "ok": 15690,
        "ko": 8
    },
    "percentiles4": {
        "total": 16207,
        "ok": 16910,
        "ko": 38
    },
    "group1": {
    "name": "t < 800 ms",
    "htmlName": "t < 800 ms",
    "count": 22748,
    "percentage": 28
},
    "group2": {
    "name": "800 ms <= t < 1200 ms",
    "htmlName": "t >= 800 ms <br> t < 1200 ms",
    "count": 27,
    "percentage": 0
},
    "group3": {
    "name": "t >= 1200 ms",
    "htmlName": "t >= 1200 ms",
    "count": 2754,
    "percentage": 3
},
    "group4": {
    "name": "failed",
    "htmlName": "failed",
    "count": 56224,
    "percentage": 69
},
    "meanNumberOfRequestsPerSecond": {
        "total": 378.4861111111111,
        "ok": 118.18981481481481,
        "ko": 260.2962962962963
    }
},
"contents": {
"req_busca-va-lida-d7f0d": {
        "type": "REQUEST",
        "name": "busca válida",
"path": "busca válida",
"pathFormatted": "req_busca-va-lida-d7f0d",
"stats": {
    "name": "busca válida",
    "numberOfRequests": {
        "total": 9590,
        "ok": 2320,
        "ko": 7270
    },
    "minResponseTime": {
        "total": 0,
        "ok": 2,
        "ko": 0
    },
    "maxResponseTime": {
        "total": 18065,
        "ok": 18065,
        "ko": 172
    },
    "meanResponseTime": {
        "total": 587,
        "ok": 2420,
        "ko": 2
    },
    "standardDeviation": {
        "total": 2838,
        "ok": 5373,
        "ko": 7
    },
    "percentiles1": {
        "total": 1,
        "ok": 82,
        "ko": 1
    },
    "percentiles2": {
        "total": 6,
        "ok": 257,
        "ko": 2
    },
    "percentiles3": {
        "total": 380,
        "ok": 16023,
        "ko": 8
    },
    "percentiles4": {
        "total": 16208,
        "ok": 17182,
        "ko": 38
    },
    "group1": {
    "name": "t < 800 ms",
    "htmlName": "t < 800 ms",
    "count": 1922,
    "percentage": 20
},
    "group2": {
    "name": "800 ms <= t < 1200 ms",
    "htmlName": "t >= 800 ms <br> t < 1200 ms",
    "count": 4,
    "percentage": 0
},
    "group3": {
    "name": "t >= 1200 ms",
    "htmlName": "t >= 1200 ms",
    "count": 394,
    "percentage": 4
},
    "group4": {
    "name": "failed",
    "htmlName": "failed",
    "count": 7270,
    "percentage": 76
},
    "meanNumberOfRequestsPerSecond": {
        "total": 44.398148148148145,
        "ok": 10.74074074074074,
        "ko": 33.657407407407405
    }
}
    },"req_criac-a-o-ce502": {
        "type": "REQUEST",
        "name": "criação",
"path": "criação",
"pathFormatted": "req_criac-a-o-ce502",
"stats": {
    "name": "criação",
    "numberOfRequests": {
        "total": 54652,
        "ok": 15525,
        "ko": 39127
    },
    "minResponseTime": {
        "total": 0,
        "ok": 1,
        "ko": 0
    },
    "maxResponseTime": {
        "total": 19999,
        "ok": 19999,
        "ko": 198
    },
    "meanResponseTime": {
        "total": 630,
        "ok": 2210,
        "ko": 2
    },
    "standardDeviation": {
        "total": 3003,
        "ok": 5315,
        "ko": 7
    },
    "percentiles1": {
        "total": 1,
        "ok": 19,
        "ko": 1
    },
    "percentiles2": {
        "total": 6,
        "ok": 87,
        "ko": 1
    },
    "percentiles3": {
        "total": 114,
        "ok": 16176,
        "ko": 8
    },
    "percentiles4": {
        "total": 16406,
        "ok": 17094,
        "ko": 39
    },
    "group1": {
    "name": "t < 800 ms",
    "htmlName": "t < 800 ms",
    "count": 13142,
    "percentage": 24
},
    "group2": {
    "name": "800 ms <= t < 1200 ms",
    "htmlName": "t >= 800 ms <br> t < 1200 ms",
    "count": 23,
    "percentage": 0
},
    "group3": {
    "name": "t >= 1200 ms",
    "htmlName": "t >= 1200 ms",
    "count": 2360,
    "percentage": 4
},
    "group4": {
    "name": "failed",
    "htmlName": "failed",
    "count": 39127,
    "percentage": 72
},
    "meanNumberOfRequestsPerSecond": {
        "total": 253.0185185185185,
        "ok": 71.875,
        "ko": 181.1435185185185
    }
}
    },"req_busca-inva-lida-b5618": {
        "type": "REQUEST",
        "name": "busca inválida",
"path": "busca inválida",
"pathFormatted": "req_busca-inva-lida-b5618",
"stats": {
    "name": "busca inválida",
    "numberOfRequests": {
        "total": 4190,
        "ok": 1117,
        "ko": 3073
    },
    "minResponseTime": {
        "total": 0,
        "ok": 0,
        "ko": 0
    },
    "maxResponseTime": {
        "total": 190,
        "ok": 190,
        "ko": 109
    },
    "meanResponseTime": {
        "total": 3,
        "ok": 4,
        "ko": 3
    },
    "standardDeviation": {
        "total": 7,
        "ok": 7,
        "ko": 7
    },
    "percentiles1": {
        "total": 1,
        "ok": 2,
        "ko": 1
    },
    "percentiles2": {
        "total": 3,
        "ok": 4,
        "ko": 2
    },
    "percentiles3": {
        "total": 9,
        "ok": 9,
        "ko": 8
    },
    "percentiles4": {
        "total": 30,
        "ok": 19,
        "ko": 35
    },
    "group1": {
    "name": "t < 800 ms",
    "htmlName": "t < 800 ms",
    "count": 1117,
    "percentage": 27
},
    "group2": {
    "name": "800 ms <= t < 1200 ms",
    "htmlName": "t >= 800 ms <br> t < 1200 ms",
    "count": 0,
    "percentage": 0
},
    "group3": {
    "name": "t >= 1200 ms",
    "htmlName": "t >= 1200 ms",
    "count": 0,
    "percentage": 0
},
    "group4": {
    "name": "failed",
    "htmlName": "failed",
    "count": 3073,
    "percentage": 73
},
    "meanNumberOfRequestsPerSecond": {
        "total": 19.39814814814815,
        "ok": 5.171296296296297,
        "ko": 14.226851851851851
    }
}
    },"req_consulta-5d76b": {
        "type": "REQUEST",
        "name": "consulta",
"path": "consulta",
"pathFormatted": "req_consulta-5d76b",
"stats": {
    "name": "consulta",
    "numberOfRequests": {
        "total": 13321,
        "ok": 6567,
        "ko": 6754
    },
    "minResponseTime": {
        "total": 0,
        "ok": 0,
        "ko": 0
    },
    "maxResponseTime": {
        "total": 186,
        "ok": 186,
        "ko": 183
    },
    "meanResponseTime": {
        "total": 3,
        "ok": 3,
        "ko": 3
    },
    "standardDeviation": {
        "total": 6,
        "ok": 6,
        "ko": 7
    },
    "percentiles1": {
        "total": 2,
        "ok": 2,
        "ko": 1
    },
    "percentiles2": {
        "total": 3,
        "ok": 4,
        "ko": 2
    },
    "percentiles3": {
        "total": 8,
        "ok": 9,
        "ko": 6
    },
    "percentiles4": {
        "total": 19,
        "ok": 17,
        "ko": 27
    },
    "group1": {
    "name": "t < 800 ms",
    "htmlName": "t < 800 ms",
    "count": 6567,
    "percentage": 49
},
    "group2": {
    "name": "800 ms <= t < 1200 ms",
    "htmlName": "t >= 800 ms <br> t < 1200 ms",
    "count": 0,
    "percentage": 0
},
    "group3": {
    "name": "t >= 1200 ms",
    "htmlName": "t >= 1200 ms",
    "count": 0,
    "percentage": 0
},
    "group4": {
    "name": "failed",
    "htmlName": "failed",
    "count": 6754,
    "percentage": 51
},
    "meanNumberOfRequestsPerSecond": {
        "total": 61.6712962962963,
        "ok": 30.40277777777778,
        "ko": 31.26851851851852
    }
}
    }
}

}